audio_toolbox/__init__.py
audio_toolbox/common.py
audio_toolbox/ffmpeg.py
audio_toolbox/sox.py
audio_toolbox-0.2.dist-info/METADATA
audio_toolbox-0.2.dist-info/RECORD
audio_toolbox-0.2.dist-info/WHEEL
audio_toolbox-0.2.dist-info/top_level.txt
